gdal2tiles/__init__.py
gdal2tiles/gdal2tiles.py
gdal2tiles/utils.py
pygdal2tiles-0.1.9.dist-info/AUTHORS.rst
pygdal2tiles-0.1.9.dist-info/LICENSE
pygdal2tiles-0.1.9.dist-info/METADATA
pygdal2tiles-0.1.9.dist-info/WHEEL
pygdal2tiles-0.1.9.dist-info/top_level.txt
pygdal2tiles-0.1.9.dist-info/RECORD
