Metadata-Version: 2.1
Name: pygdal2tiles
Version: 0.1.9
Summary: A fork of gdal2tiles without gdal specified so that it can easily be installed in a virtual environment. A python library for generating map tiles based on gdal2tiles.py script.
Home-page: https://github.com/nationaldrones/gdal2tiles
Author: National Drones
Author-email: smartdata@nationaldrones.com
License: MIT license
Keywords: gdal2tiles
Platform: UNKNOWN
Classifier: Development Status :: 2 - Pre-Alpha
Classifier: Intended Audience :: Developers
Classifier: License :: OSI Approved :: MIT License
Classifier: Natural Language :: English
Classifier: Programming Language :: Python :: 2
Classifier: Programming Language :: Python :: 2.7
Classifier: Programming Language :: Python :: 3
Classifier: Programming Language :: Python :: 3.4
Classifier: Programming Language :: Python :: 3.5
Classifier: Programming Language :: Python :: 3.6
Provides-Extra: billiard
Requires-Dist: billiard ; extra == 'billiard'
